whatsapp_auto/__init__.py
whatsapp_auto/exception.py
whatsapp_auto/main.py
whatsapp_auto-1.1.dist-info/LICENSE
whatsapp_auto-1.1.dist-info/METADATA
whatsapp_auto-1.1.dist-info/WHEEL
whatsapp_auto-1.1.dist-info/top_level.txt
whatsapp_auto-1.1.dist-info/RECORD
