Metadata-Version: 2.1
Name: whatsapp-auto
Version: 1.1
Summary: WhatsApp Web Automation Library using selenium
Author-email: Anish <anishshakthivelnadar@gmail.com>
Project-URL: Homepage, https://github.com/Anish0612/whatsapp-auto
Project-URL: Bug Tracker, https://github.com/Anish0612/whatsapp-auto/issues
Classifier: Programming Language :: Python :: 3
Classifier: License :: OSI Approved :: MIT License
Classifier: Operating System :: OS Independent
Requires-Python: >=3.7
License-File: LICENSE
Requires-Dist: selenium
Requires-Dist: undetected-chromedriver
